koinmal/Prihops.py
koinmal/__init__.py
koinmal-0.5.dist-info/licenses/LICENSE
koinmal-0.5.dist-info/METADATA
koinmal-0.5.dist-info/WHEEL
koinmal-0.5.dist-info/top_level.txt
koinmal-0.5.dist-info/RECORD
