Metadata-Version: 2.4
Name: koinmal
Version: 0.5
Summary: maths integration
Home-page: 
Author: Bedirhan
Author-email: bedirhan.oytpass@gmail.com
License: Custom Software License for koinmal
Keywords: maths,entegration
Classifier: Programming Language :: Python :: 3
Classifier: License :: Other/Proprietary License
Classifier: Operating System :: OS Independent
License-File: LICENSE
Dynamic: author
Dynamic: author-email
Dynamic: classifier
Dynamic: description
Dynamic: description-content-type
Dynamic: keywords
Dynamic: license
Dynamic: license-file
Dynamic: summary
